odoo/addons/product_pricelist_button_box/README.rst
odoo/addons/product_pricelist_button_box/__init__.py
odoo/addons/product_pricelist_button_box/__manifest__.py
odoo/addons/product_pricelist_button_box/i18n/product_pricelist_button_box.pot
odoo/addons/product_pricelist_button_box/readme/CONTRIBUTORS.rst
odoo/addons/product_pricelist_button_box/readme/DESCRIPTION.rst
odoo/addons/product_pricelist_button_box/static/description/icon.png
odoo/addons/product_pricelist_button_box/static/description/index.html
odoo/addons/product_pricelist_button_box/views/product_pricelist.xml
odoo13_addon_product_pricelist_button_box-13.0.1.0.1.dist-info/METADATA
odoo13_addon_product_pricelist_button_box-13.0.1.0.1.dist-info/WHEEL
odoo13_addon_product_pricelist_button_box-13.0.1.0.1.dist-info/top_level.txt
odoo13_addon_product_pricelist_button_box-13.0.1.0.1.dist-info/RECORD
